harlequin_bigquery/__init__.py
harlequin_bigquery/adapter.py
harlequin_bigquery/cli_options.py
harlequin_bigquery/functions.py
harlequin_bigquery/keywords.py
harlequin_bigquery/py.typed
harlequin_bigquery-1.0.3.dist-info/LICENSE
harlequin_bigquery-1.0.3.dist-info/METADATA
harlequin_bigquery-1.0.3.dist-info/WHEEL
harlequin_bigquery-1.0.3.dist-info/entry_points.txt
harlequin_bigquery-1.0.3.dist-info/RECORD
