Metadata-Version: 2.3
Name: harlequin_bigquery
Version: 1.0.3
Summary: A Harlequin adapter for Google BigQuery.
License: MIT
Author: Josh Temple
Author-email: tconbeer@users.noreply.github.com
Requires-Python: >=3.8.1,<4.0
Classifier: License :: OSI Approved :: MIT License
Classifier: Programming Language :: Python :: 3
Classifier: Programming Language :: Python :: 3.9
Classifier: Programming Language :: Python :: 3.10
Classifier: Programming Language :: Python :: 3.11
Classifier: Programming Language :: Python :: 3.12
Classifier: Programming Language :: Python :: 3.13
Requires-Dist: google-cloud-bigquery (>=3.14.1,<4.0.0)
Requires-Dist: google-cloud-bigquery-storage (>=2.24.0,<3.0.0)
Requires-Dist: harlequin (>=1.7,<3)
